playwright_spider_utils/__init__.py
playwright_spider_utils/file_extractors.py
playwright_spider_utils/link_extractors.py
playwright_spider_utils-0.1.2.dist-info/LICENSE
playwright_spider_utils-0.1.2.dist-info/METADATA
playwright_spider_utils-0.1.2.dist-info/WHEEL
playwright_spider_utils-0.1.2.dist-info/RECORD
